djangodbu/__init__.py
djangodbu/ago.py
djangodbu/shell.py
djangodbu/shellprintmodel.py
djangodbu/sql.py
djangodbu/terminalsize.py
djangodbu/unihl.py
djangodbu/utils.py
djangodbu-0.1.8.dist-info/METADATA
djangodbu-0.1.8.dist-info/WHEEL
djangodbu-0.1.8.dist-info/licenses/LICENSE.txt
djangodbu-0.1.8.dist-info/RECORD
