Metadata-Version: 2.3
Name: djangodbu
Version: 0.1.8
Summary: Tools for debugging Django ORM, pprint models
Project-URL: Homepage, https://github.com/mulderns/djangodbu
Project-URL: Bug Tracker, https://github.com/mulderns/djangodbu/issues
Author-email: Valtteri Kortesmaa <mulperns+please-remove-this-part-and-change-p-to-d@iki.fi>
Keywords: debug,django,orm,pprint,shell_plus
Classifier: Development Status :: 4 - Beta
Classifier: Intended Audience :: Developers
Classifier: License :: OSI Approved :: MIT License
Classifier: Programming Language :: Python :: 3
Classifier: Topic :: Software Development
Requires-Python: >=3.7
Requires-Dist: sqlparse
